examples/__init__.py
examples/check_s3_bucket.py
examples/plugin_config.py
examples/rule_testing.py
examples/virtual_plugin_config.py
notebooks/mkdataset.py
tests/_linter/__init__.py
tests/_linter/test_rulectx.py
tests/cli/__init__.py
tests/cli/helpers.py
tests/cli/test_config.py
tests/cli/test_main.py
tests/cli/configs/recommended.py
tests/formatters/__init__.py
tests/formatters/helpers.py
tests/formatters/test_html.py
tests/formatters/test_json.py
tests/formatters/test_simple.py
tests/plugins/__init__.py
tests/plugins/core/__init__.py
tests/plugins/core/test_plugin.py
tests/plugins/core/rules/__init__.py
tests/plugins/core/rules/test_access_latency.py
tests/plugins/core/rules/test_content_desc.py
tests/plugins/core/rules/test_conventions.py
tests/plugins/core/rules/test_coords_for_dims.py
tests/plugins/core/rules/test_grid_mappings.py
tests/plugins/core/rules/test_lat_lon_coordinate.py
tests/plugins/core/rules/test_no_empty_attrs.py
tests/plugins/core/rules/test_no_empty_chunks.py
tests/plugins/core/rules/test_time_coordinate.py
tests/plugins/core/rules/test_var_desc.py
tests/plugins/core/rules/test_var_flags.py
tests/plugins/core/rules/test_var_missing_data.py
tests/plugins/core/rules/test_var_units.py
tests/plugins/xcube/__init__.py
tests/plugins/xcube/helpers.py
tests/plugins/xcube/test_plugin.py
tests/plugins/xcube/test_util.py
tests/plugins/xcube/processors/__init__.py
tests/plugins/xcube/processors/test_mldataset.py
tests/plugins/xcube/rules/__init__.py
tests/plugins/xcube/rules/test_any_spatial_data_var.py
tests/plugins/xcube/rules/test_cube_dims_order.py
tests/plugins/xcube/rules/test_data_var_colors.py
tests/plugins/xcube/rules/test_dataset_title.py
tests/plugins/xcube/rules/test_grid_mapping_naming.py
tests/plugins/xcube/rules/test_increasing_time.py
tests/plugins/xcube/rules/test_lat_lon_naming.py
tests/plugins/xcube/rules/test_ml_dataset_meta.py
tests/plugins/xcube/rules/test_ml_dataset_time.py
tests/plugins/xcube/rules/test_ml_dataset_xy.py
xrlint-0.5.1.dist-info/LICENSE
xrlint-0.5.1.dist-info/METADATA
xrlint-0.5.1.dist-info/WHEEL
xrlint-0.5.1.dist-info/entry_points.txt
xrlint-0.5.1.dist-info/top_level.txt
xrlint-0.5.1.dist-info/RECORD
