Metadata-Version: 2.2
Name: xrlint
Version: 0.5.1
Summary: A linter for xarray datasets.
Author: Norman Fomferra (Brockmann Consult GmbH)
License: MIT
Project-URL: Documentation, https://bcdev.github.io/xrlint
Project-URL: Repository, https://github.com/bcdev/xrlint
Project-URL: Changelog, https://github.com/bcdev/xrlint/blob/main/CHANGES.md
Project-URL: Issues, https://github.com/bcdev/xrlint/issues
Keywords: xarray,data-science,cf,metadata
Classifier: Development Status :: 5 - Production/Stable
Classifier: Intended Audience :: Science/Research
Classifier: Intended Audience :: Developers
Classifier: License :: OSI Approved :: MIT License
Classifier: Programming Language :: Python :: 3
Classifier: Programming Language :: Python :: 3.10
Classifier: Programming Language :: Python :: 3.11
Classifier: Programming Language :: Python :: 3.12
Classifier: Programming Language :: Python :: 3.13
Classifier: Topic :: Software Development
Classifier: Topic :: Scientific/Engineering
Classifier: Typing :: Typed
Classifier: Operating System :: Microsoft :: Windows
Classifier: Operating System :: POSIX
Classifier: Operating System :: Unix
Classifier: Operating System :: MacOS
Requires-Python: >=3.10
License-File: LICENSE
Requires-Dist: click
Requires-Dist: fsspec
Requires-Dist: pyyaml
Requires-Dist: tabulate
Requires-Dist: xarray
Provides-Extra: dev
Requires-Dist: build; extra == "dev"
Requires-Dist: hatch; extra == "dev"
Requires-Dist: isort; extra == "dev"
Requires-Dist: pytest; extra == "dev"
Requires-Dist: pytest-cov; extra == "dev"
Requires-Dist: ruff; extra == "dev"
Requires-Dist: twine; extra == "dev"
Requires-Dist: dask; extra == "dev"
Requires-Dist: netcdf4; extra == "dev"
Requires-Dist: numpy; extra == "dev"
Requires-Dist: pandas; extra == "dev"
Requires-Dist: zarr!=3.0.0,!=3.0.1,>=2.18; extra == "dev"
Provides-Extra: doc
Requires-Dist: mkdocs; extra == "doc"
Requires-Dist: mkdocs-autorefs; extra == "doc"
Requires-Dist: mkdocs-material; extra == "doc"
Requires-Dist: mkdocstrings; extra == "doc"
Requires-Dist: mkdocstrings-python; extra == "doc"
